pytest_fixture_classes/__init__.py
pytest_fixture_classes/fixture_class.py
pytest_fixture_classes/py.typed
pytest_fixture_classes-1.0.4.dist-info/METADATA
pytest_fixture_classes-1.0.4.dist-info/WHEEL
pytest_fixture_classes-1.0.4.dist-info/licenses/LICENSE
pytest_fixture_classes-1.0.4.dist-info/RECORD
