Metadata-Version: 2.4
Name: pytest-fixture-classes
Version: 1.0.4
Summary: Fixtures as classes that work well with dependency injection, autocompletetion, type checkers, and language servers
Project-URL: Documentation, https://github.com/zmievsa/pytest-fixture-classes
Project-URL: Repository, https://github.com/zmievsa/pytest-fixture-classes
Author-email: Stanislav Zmiev <zmievsa@gmail.com>
License: MIT
License-File: LICENSE
Keywords: annotations,factory fixtures,fixtures,py.test,pytest,type hints
Classifier: Development Status :: 5 - Production/Stable
Classifier: Environment :: Console
Classifier: Framework :: Pytest
Classifier: Intended Audience :: Developers
Classifier: Operating System :: Microsoft :: Windows
Classifier: Operating System :: POSIX
Classifier: Operating System :: Unix
Classifier: Topic :: Software Development :: Testing
Classifier: Topic :: Utilities
Requires-Python: >=3.7
Requires-Dist: typing-extensions>=4.4.0
